setup.py
hongchalib/__init__.py
hongchalib/hongchalib.py
hongchalib/main.py
hongchalib.egg-info/PKG-INFO
hongchalib.egg-info/SOURCES.txt
hongchalib.egg-info/dependency_links.txt
hongchalib.egg-info/top_level.txt