Metadata-Version: 1.1
Name: hongchalib
Version: 0.1.0
Summary: 这只是一个方法快捷库
Home-page: https://github.com/
Author: haowen zhang
Author-email: 806670753@qq.com
License: UNKNOWN
Platform: UNKNOWN
Classifier: Programming Language :: Python :: 3
Classifier: License :: OSI Approved :: MIT License
Classifier: Operating System :: OS Independent
